{
    "P1505": "male",
    "P1506": "female",
    "P1123": "male",
    "P1388": "female",
    "P3722": "male",
    "P3723": "male",
    "P1306A": "male",
    "P1305A": "female",
    "P1319": "female",
    "P1318": "female",
    "P1766": "male",
    "P1420": "female",
    "P1304A": "male",
    "P1309A": "male",
    "P1308A": "female",
    "P1352": "male",
    "P1679": "male",
    "P1273A": "female",
    "P1274A": "male",
    "P1840": "female",
    "P1841": "female",
    "P1292A": "female",
    "P1294A": "female",
    "P1682": "female",
    "P1681": "male",
    "P2518": "male",
    "P2519": "male",
    "P2072A": "female",
    "P1307A": "female",
    "P1272A": "female",
    "P1293A": "female",
    "P1274": "male",
    "P1632": "female",
    "P1633": "female",
    "P1678": "male",
    "P1541": "male",
    "P0092": "male",
    "P0093": "female",
    "P0421": "male",
    "P0422": "male",
    "P0469": "male",
    "P0470": "male",
    "P0564": "male",
    "P0561": "female",
    "P0562": "female",
    "P0739": "female",
    "P0740": "female",
    "P0999": "female",
    "P0977": "female",
    "P1009": "male",
    "P1007": "male",
    "P0223": "male",
    "P0222": "female",
    "P0743": "female",
    "P0742": "male",
    "P0399": "female",
    "P1144": "female",
    "P1247": "female",
    "P0380": "female",
    "P0381": "male",
    "P0695": "female",
    "P0694": "male",
    "P0832": "male",
    "P0831": "male",
    "P0043": "male",
    "P0108": "male",
    "P0868": "female",
    "P1033": "male",
    "P0655": "male",
    "P0326": "male",
    "P1195": "male",
    "P1194": "female",
    "P1298": "female",
    "P1297": "male",
    "P2422": "female",
    "P2423": "male",
    "P2760": "male",
    "P2759": "female",
    "P1125": "male",
    "P1124": "female",
    "P1288": "female",
    "P1287": "female",
    "P1405": "female",
    "P1406": "female",
    "P2548": "female",
    "P2547": "male",
    "P1074": "male",
    "P1075": "male",
    "P1397": "female",
    "P1396": "female",
    "P5124": "male",
    "P5125": "female",
    "P5145": "male",
    "P5191": "male",
    "P5192": "male",
    "P1089": "male",
    "P1088": "male",
    "P1299": "female",
    "P1454": "male",
    "P1455": "male",
    "P1657": "male",
    "P1656": "female",
    "P4603": "male",
    "P4602": "female",
    "P2962": "male",
    "P2963": "female",
    "P2634": "female",
    "P2296": "female",
    "P4892": "male",
    "P4893": "female",
    "P1810": "female",
    "P1811": "female",
    "P2597": "male",
    "P2596": "male",
    "P1119": "male",
    "P1118": "male",
    "P4934": "female",
    "P4935": "male",
    "P1467": "female",
    "P1466": "female",
    "P2454": "male",
    "P4104": "male",
    "P4235": "male",
    "P1303": "male",
    "P1302": "female",
    "P2455": "male",
    "P3165": "female",
    "P3164": "female",
    "P4105": "male",
    "P1519": "female",
    "P1518": "male",
    "P3359": "male",
    "P3358": "male",
    "P5060": "female",
    "P5061": "female",
    "P5493": "male",
    "P5038": "female",
    "P1596": "female",
    "P5607": "male",
    "P5039": "female",
    "P5055": "female",
    "P5054": "male",
    "P5375": "female",
    "P5266": "female",
    "P5267": "female",
    "P5328": "male",
    "P5329": "male",
    "P5678": "female",
    "P5679": "female",
    "P0799": "male",
    "P0844A": "male",
    "P0947": "male",
    "P0816": "male",
    "P0383": "male",
    "P0731": "male",
    "P1281A": "female",
    "P1347A": "male",
    "P1282A": "female",
    "P0299A": "male",
    "P0845": "female",
    "P0847": "female",
    "P0852": "male",
    "P1627": "male",
    "P1694": "female",
    "P2767": "female",
    "P2766": "male",
    "P1277A": "female",
    "P1346A": "male",
    "P1316": "female",
    "P2039": "female",
    "P1437": "male",
    "P1276A": "male",
    "P1693": "male",
    "P1436": "male",
    "P1628": "male",
    "P1634": "female",
    "P0801": "male",
    "P1275A": "female",
    "P2040": "male",
    "P1317": "female",
    "P1618": "female",
    "P1555": "male",
    "P4544": "male",
    "P1606": "female",
    "P4044": "male",
    "P4139": "female",
    "P1528": "female",
    "P1607": "male",
    "P4045": "male",
    "P1554": "male",
    "P1529": "male",
    "P3758": "male",
    "P0061": "female",
    "P0059A": "female",
    "P0064": "male",
    "P0066": "male",
    "P0085": "female",
    "P0087": "male",
    "P0027A": "female",
    "P0089": "male",
    "P0029A": "female",
    "P0091": "female",
    "P0068": "female",
    "P0088": "female",
    "P0062": "male",
    "P0040A": "male",
    "P0060": "male",
    "P0063": "female",
    "P0067A": "male",
    "P0105": "male",
    "P0086": "female",
    "P0084": "male",
    "P0106": "female",
    "P0065": "female",
    "P0090": "male",
    "P0109": "female",
    "P0110": "male",
    "P0111": "male",
    "P0128": "female",
    "P0130": "male",
    "P0107": "female",
    "P0079": "female",
    "P0127": "male",
    "P0129": "male",
    "P0026A": "female",
    "P0150A": "female",
    "P0153": "female",
    "P0131": "male",
    "P0133": "male",
    "P0134": "male",
    "P0152": "male",
    "P0151": "female",
    "P0132": "male",
    "P0028A": "female",
    "P0144": "male",
    "P0003A": "female",
    "P0194": "male",
    "P0197": "male",
    "P0004A": "female",
    "P0198": "female",
    "P0156": "female",
    "P0157": "female",
    "P0189": "male",
    "P0190": "female",
    "P0191": "female",
    "P0006A": "male",
    "P0154": "female",
    "P0187": "male",
    "P0195": "male",
    "P0188": "female",
    "P0192": "female",
    "P0196": "male",
    "P0155": "male",
    "P0002": "female",
    "P0199": "male",
    "P0203": "male",
    "P0231": "female",
    "P0234": "male",
    "P0236": "male",
    "P0202": "female",
    "P0193": "female",
    "P0237": "male",
    "P0228": "female",
    "P0229": "male",
    "P0233": "male",
    "P0230": "male",
    "P0232": "male",
    "P0011": "female",
    "P0238": "female",
    "P0235": "male",
    "P0012": "female",
    "P0240": "female",
    "P0264": "male",
    "P0005A": "male",
    "P0257": "male",
    "P0259": "male",
    "P0263": "female",
    "P0266": "male",
    "P0186": "female",
    "P0268": "female",
    "P0269": "male",
    "P0270": "female",
    "P0271": "female",
    "P0274": "female",
    "P0267": "female",
    "P0272": "male",
    "P0262": "female",
    "P0273": "male",
    "P0265": "female",
    "P0312": "male",
    "P0317": "female",
    "P0319": "male",
    "P0316": "male",
    "P0325": "female",
    "P0315": "female",
    "P0318": "male",
    "P0320": "female",
    "P0324": "male",
    "P0313": "male",
    "P0322": "male",
    "P0314": "female",
    "P0327": "female",
    "P0323": "male",
    "P0321": "female",
    "P0364": "male",
    "P0367": "female",
    "P0356": "male",
    "P0355": "female",
    "P0050": "female",
    "P0357": "female",
    "P0360": "female",
    "P0361": "female",
    "P0369": "male",
    "P0394": "female",
    "P0085A": "female",
    "P0363": "male",
    "P0358": "female",
    "P0365": "female",
    "P0359": "male",
    "P0362": "female",
    "P0366": "male",
    "P0368": "male",
    "P0396": "female",
    "P0442": "female",
    "P0448": "female",
    "P0450": "female",
    "P0451": "male",
    "P0454": "male",
    "P0397": "male",
    "P0402": "female",
    "P0403": "male",
    "P0407": "female",
    "P0444": "female",
    "P0443": "female",
    "P0382": "male",
    "P0449": "male",
    "P0398": "female",
    "P0408": "male",
    "P0310": "female",
    "P0487": "male",
    "P0488": "male",
    "P0426": "female",
    "P0532": "male",
    "P0492": "female",
    "P0494": "female",
    "P0486": "male",
    "P0489": "female",
    "P0493": "female",
    "P0498": "female",
    "P0499": "male",
    "P0241A": "female",
    "P0497": "female",
    "P0229A": "male",
    "P0107A": "female",
    "P0490": "female",
    "P0495": "female",
    "P0524": "female",
    "P0193A": "female",
    "P0092A": "female",
    "P0574": "male",
    "P0359A": "female",
    "P0582": "female",
    "P0569": "female",
    "P0571": "male",
    "P0576": "male",
    "P0539": "male",
    "P0577": "male",
    "P0581": "male",
    "P0602A": "female",
    "P0570": "female",
    "P0575": "male",
    "P0580": "female",
    "P0573": "female",
    "P0371": "female",
    "P0565": "female",
    "P0383A": "female",
    "P0250A": "female",
    "P0414": "female",
    "P0074": "female",
    "P0618": "male",
    "P0508": "male",
    "P0262A": "female",
    "P0621": "male",
    "P0625": "female",
    "P0626": "female",
    "P0658A": "female",
    "P0042A": "female",
    "P0659": "female",
    "P0587": "male",
    "P0070": "female",
    "P0622": "male",
    "P0323A": "male",
    "P0623": "female",
    "P0627": "female",
    "P0615": "male",
    "P0035": "female",
    "P0686": "male",
    "P0690": "male",
    "P0692": "male",
    "P0332": "female",
    "P0069": "male",
    "P0348": "male",
    "P0680": "female",
    "P0687": "male",
    "P0662": "female",
    "P0683": "female",
    "P0691": "male",
    "P0682A": "female",
    "P0389": "male",
    "P0681": "male",
    "P0058": "male",
    "P0377": "female",
    "P0676": "male",
    "P0185A": "male",
    "P0825A": "female",
    "P0765": "female",
    "P0794": "female",
    "P0506": "female",
    "P0822": "female",
    "P0802": "female",
    "P0817": "female",
    "P0798": "male",
    "P0230A": "male",
    "P0800": "female",
    "P0012A": "female",
    "P0823": "male",
    "P0827": "female",
    "P0764": "male",
    "P0830": "male",
    "P0122": "female",
    "P0737": "female",
    "P0851": "female",
    "P0826": "male",
    "P0460": "female",
    "P0407A": "female",
    "P0860": "male",
    "P0500": "female",
    "P0833": "female",
    "P0179": "female",
    "P0124A": "female",
    "P0835": "female",
    "P0829": "male",
    "P0861": "female",
    "P0397A": "male",
    "P0870": "female",
    "P0196A": "male",
    "P0002A": "female",
    "P0894": "female",
    "P0867": "female",
    "P0123": "female",
    "P0869A": "male",
    "P0893": "male",
    "P0015": "female",
    "P0895": "male",
    "P0902": "male",
    "P0328A": "female",
    "P0896": "female",
    "P0464A": "male",
    "P0920A": "female",
    "P0927": "male",
    "P0919": "male",
    "P0921": "female",
    "P0906": "male",
    "P0924": "male",
    "P0909": "male",
    "P0806": "female",
    "P0903": "female",
    "P0120": "female",
    "P0925": "female",
    "P0935A": "female",
    "P0940": "male",
    "P0946": "female",
    "P0958": "male",
    "P0964": "female",
    "P0933": "male",
    "P0678": "female",
    "P0955": "female",
    "P0282": "female",
    "P0396A": "female",
    "P0934": "female",
    "P0939": "male",
    "P0388A": "female",
    "P0928": "male",
    "P0708": "female",
    "P0862": "female",
    "P0185": "male",
    "P0966": "female",
    "P0969": "female",
    "P0976A": "female",
    "P0980": "female",
    "P0978": "female",
    "P0805": "male",
    "P0965": "male",
    "P0973": "female",
    "P0974": "female",
    "P0970": "female",
    "P0975": "male",
    "P0921A": "female",
    "P0120A": "female",
    "P0986": "female",
    "P0989": "male",
    "P0073": "female",
    "P0984": "male",
    "P0985": "male",
    "P0929": "female",
    "P0014": "female",
    "P0180A": "female",
    "P0996": "male",
    "P0395": "male",
    "P0967": "female",
    "P0997": "female",
    "P0991": "female",
    "P0994": "male",
    "P0553": "female",
    "P0990": "male",
    "P1011": "male",
    "P0998": "female",
    "P1025": "male",
    "P0210A": "female",
    "P1036": "male",
    "P0702": "male",
    "P1004": "female",
    "P0145": "male",
    "P1001": "female",
    "P1002": "female",
    "P1010": "male",
    "P1017": "male",
    "P1023": "male",
    "P0557A": "male",
    "P0204": "male",
    "P0845A": "female",
    "P1038": "female",
    "P0075": "male",
    "P0799A": "male",
    "P1049": "female",
    "P1047A": "female",
    "P0974A": "female",
    "P0707A": "female",
    "P1048": "female",
    "P1050": "male",
    "P0710": "female",
    "P1061": "male",
    "P1062": "female",
    "P0320A": "female",
    "P0744": "female",
    "P0437A": "female",
    "P0047": "female",
    "P1094A": "female",
    "P0946A": "female",
    "P0955A": "female",
    "P0878A": "male",
    "P1102A": "female",
    "P1100A": "female",
    "P0728": "female",
    "P1099A": "male",
    "P0041A": "female",
    "P1103A": "male",
    "P1104A": "male",
    "P0789A": "male",
    "P1106A": "male",
    "P0789": "male",
    "P1115A": "male",
    "P1114A": "male",
    "P0871A": "male",
    "P1124A": "female",
    "P0300": "female",
    "P0476": "female",
    "P1024A": "female",
    "P1143": "male",
    "P1139A": "female",
    "P0744A": "female",
    "P0989A": "male",
    "P0933A": "male",
    "P0893A": "female",
    "P0861A": "female",
    "P1147A": "male",
    "P1148A": "female",
    "P1152A": "female",
    "P1149A": "female",
    "P1151A": "female",
    "P0546": "female",
    "P0115": "male",
    "P1154A": "female",
    "P1006": "female",
    "P1155A": "female",
    "P0106A": "female",
    "P0791": "female",
    "P1264A": "female",
    "P1263A": "male",
    "P1286A": "female",
    "P1265A": "male",
    "P1268A": "male",
    "P1283A": "male",
    "P1260A": "female",
    "P1266A": "female",
    "P1271A": "male",
    "P1289A": "female",
    "P1261A": "female",
    "P1270A": "male",
    "P1262A": "female",
    "P1269A": "male",
    "P1285A": "male",
    "P1267A": "male",
    "P1288A": "male",
    "P1280A": "male",
    "P1279A": "male",
    "P1284A": "female",
    "P1287A": "female",
    "P1278A": "male",
    "P1290A": "male",
    "P1310A": "male",
    "P1318A": "female",
    "P1320A": "male",
    "P1323A": "male",
    "P1324A": "male",
    "P1325A": "male",
    "P1334A": "female",
    "P1336A": "female",
    "P1337A": "female",
    "P1316A": "male",
    "P1319A": "male",
    "P1329A": "male",
    "P1327A": "male",
    "P1343A": "female",
    "P1344A": "female",
    "P1298A": "male",
    "P1299A": "male",
    "P1321A": "male",
    "P1326A": "male",
    "P1312A": "male",
    "P1330A": "female",
    "P1317A": "male",
    "P1322A": "male",
    "P1345A": "female",
    "P1338A": "female",
    "P1335A": "female",
    "P1339A": "female",
    "P1291A": "male",
    "P1311A": "female",
    "P1300A": "male",
    "P1328A": "female",
    "P1114": "female",
    "P1115": "female",
    "P1180": "female",
    "P1214": "female",
    "P1228": "female",
    "P1304": "male",
    "P1320": "female",
    "P1327": "male",
    "P1182": "female",
    "P1212": "female",
    "P1215": "female",
    "P1063": "female",
    "P1310": "male",
    "P1322": "female",
    "P1191": "male",
    "P1213": "male",
    "P1305": "female",
    "P1326": "female",
    "P1176": "female",
    "P1177": "male",
    "P1181": "female",
    "P1229": "male",
    "P1323": "female",
    "P1315": "female",
    "P1314": "female",
    "P1321": "female",
    "P1190": "female",
    "P1308": "female",
    "P1309": "male",
    "P1183": "female",
    "P1248": "female",
    "P1272": "female",
    "P1311": "male",
    "P1312": "male",
    "P1313": "female",
    "P1334": "female",
    "P1509": "female",
    "P1511": "female",
    "P1565": "female",
    "P1210": "female",
    "P1531": "female",
    "P1470": "female",
    "P1047": "male",
    "P1330": "female",
    "P1392": "female",
    "P1391": "female",
    "P1512": "female",
    "P1516": "female",
    "P1507": "male",
    "P1265": "male",
    "P1513": "male",
    "P1564": "male",
    "P1331": "female",
    "P1503": "male",
    "P1522": "male",
    "P1523": "male",
    "P1338": "male",
    "P1504": "female",
    "P1508": "male",
    "P1566": "female",
    "P1333": "female",
    "P1472": "female",
    "P1335": "female",
    "P1510": "female",
    "P1517": "female",
    "P1339": "female",
    "P1521": "female",
    "P1526": "female",
    "P1527": "female",
    "P1471": "female",
    "P1332": "male",
    "P1530": "female",
    "P1567": "male",
    "P1568": "female",
    "P1570": "male",
    "P1571": "male",
    "P1553": "female",
    "P1644": "female",
    "P1635": "female",
    "P1638": "female",
    "P1641": "male",
    "P1649": "male",
    "P1538": "female",
    "P1640": "female",
    "P1651": "male",
    "P1654": "male",
    "P1676": "male",
    "P1543": "male",
    "P1621": "male",
    "P1552": "male",
    "P1629": "female",
    "P1639": "male",
    "P1617": "female",
    "P1616": "male",
    "P1137": "female",
    "P1646": "male",
    "P1613": "female",
    "P1642": "male",
    "P1653": "male",
    "P1622": "female",
    "P1643": "female",
    "P1650": "female",
    "P1645": "male",
    "P1636": "female",
    "P1637": "male",
    "P1620": "female",
    "P1625": "female",
    "P1677": "male",
    "P1624": "female",
    "P1573": "male",
    "P1572": "female",
    "P1652": "male",
    "P1569": "male",
    "P1655": "male",
    "P1626": "female",
    "P1574": "male",
    "P1623": "female",
    "P1630": "male",
    "P1631": "male",
    "P1683": "male",
    "P1686": "female",
    "P1685": "male",
    "P1692": "female",
    "P1716": "male",
    "P1717": "female",
    "P1772": "female",
    "P1782": "male",
    "P1680": "female",
    "P1689": "female",
    "P1714": "male",
    "P1715": "female",
    "P1784": "female",
    "P1707": "female",
    "P1721": "female",
    "P1230": "male",
    "P1684": "female",
    "P1353": "male",
    "P1722": "male",
    "P1768": "female",
    "P1747": "male",
    "P1344": "male",
    "P1708": "female",
    "P1690": "female",
    "P1709": "female",
    "P1343": "female",
    "P1227": "male",
    "P1612": "female",
    "P1780": "female",
    "P1783": "male",
    "P1767": "female",
    "P1781": "female",
    "P1719": "male",
    "P1785": "female",
    "P1718": "male",
    "P1246": "male",
    "P1609": "male",
    "P1608": "male",
    "P1537": "male",
    "P1691": "female",
    "P1219": "female",
    "P1788": "male",
    "P1790": "male",
    "P1231": "female",
    "P1804": "female",
    "P1003": "female",
    "P1218": "female",
    "P1805": "female",
    "P1809": "female",
    "P1786": "male",
    "P1789": "male",
    "P1792": "male",
    "P1779": "female",
    "P1740": "female",
    "P1791": "male",
    "P1801": "female",
    "P1514": "male",
    "P1226": "female",
    "P1233": "male",
    "P1756": "female",
    "P1725": "male",
    "P1800": "female",
    "P1750": "female",
    "P1807": "female",
    "P1808": "female",
    "P1775": "female",
    "P1793": "female",
    "P1754": "female",
    "P1806": "female",
    "P1816": "male",
    "P1746": "male",
    "P1515": "female",
    "P1755": "female",
    "P1724": "female",
    "P1815": "female",
    "P1733": "female",
    "P1776": "male",
    "P1832": "female",
    "P1812": "female",
    "P1763": "female",
    "P1824": "male",
    "P1813": "female",
    "P1831": "female",
    "P1817": "female",
    "P1833": "female",
    "P1186": "male",
    "P1834": "female",
    "P1835": "male",
    "P1846": "female",
    "P1848": "male",
    "P1743": "female",
    "P1825": "male",
    "P1839": "female",
    "P1844": "male",
    "P1850": "female",
    "P1836": "female",
    "P1842": "female",
    "P1251": "male",
    "P1845": "female",
    "P1847": "female",
    "P1849": "female",
    "P1837": "male",
    "P1843": "female",
    "P1838": "female",
    "P1851": "male",
    "P1264": "female",
    "P1728": "male",
    "P1026": "male",
    "P1855": "female",
    "P1861": "female",
    "P1271": "female",
    "P1795": "female",
    "P1742": "male",
    "P1723": "male",
    "P1857": "female",
    "P1015": "male",
    "P1853": "female",
    "P1864": "male",
    "P1852": "female",
    "P1744": "female",
    "P1243": "male",
    "P1856": "male",
    "P1862": "male",
    "P1735": "female",
    "P1758": "female",
    "P1502": "male",
    "P1858": "female",
    "P1863": "male",
    "P1854": "female",
    "P1876": "male",
    "P1739": "male",
    "P1760": "female",
    "P1867": "female",
    "P1761": "female",
    "P1869": "male",
    "P1240": "male",
    "P1870": "male",
    "P1778": "female",
    "P1042": "female",
    "P1866": "female",
    "P1239": "female",
    "P1263": "male",
    "P1737": "female",
    "P1865": "female",
    "P1873": "female",
    "P1942": "male",
    "P2077": "female",
    "P2271": "female",
    "P2419": "female",
    "P2613": "male",
    "P2632": "female",
    "P1889": "female",
    "P2654": "female",
    "P1872": "female",
    "P1925": "female",
    "P2420": "male",
    "P2639": "female",
    "P1963": "female",
    "P1727": "female",
    "P2621": "female",
    "P1005": "male",
    "P2070": "male",
    "P1232": "female",
    "P2659": "male",
    "P2402": "female",
    "P2023": "female",
    "P1008": "male",
    "P2633": "male",
    "P2038": "male",
    "P2612": "female",
    "P1878": "male",
    "P1934": "female",
    "P1745": "male",
    "P2570": "male",
    "P2569": "female",
    "P2662": "male",
    "P2154": "female",
    "P2727": "female",
    "P2730": "female",
    "P2731": "female",
    "P2734": "female",
    "P2637": "male",
    "P2699": "female",
    "P2665": "male",
    "P2663": "female",
    "P2241": "female",
    "P2691": "male",
    "P2011": "female",
    "P2698": "female",
    "P2686": "male",
    "P2627": "male",
    "P2696": "male",
    "P2674": "female",
    "P2671": "female",
    "P2735": "male",
    "P2647": "female",
    "P2684": "male",
    "P2733": "female",
    "P2729": "male",
    "P2164": "female",
    "P2732": "female",
    "P2726": "female",
    "P2615": "male",
    "P2145": "male",
    "P2406": "female",
    "P2619": "female",
    "P2689": "female",
    "P2687": "female",
    "P2712": "male",
    "P2697": "male",
    "P2737": "female",
    "P2745": "male",
    "P2756": "male",
    "P2763": "male",
    "P1014": "male",
    "P2680": "male",
    "P2675": "male",
    "P2668": "male",
    "P2651": "male",
    "P1254": "male",
    "P1000": "male",
    "P2739": "female",
    "P2765": "male",
    "P2736": "male",
    "P2620": "male",
    "P2628": "male",
    "P2667": "male",
    "P2677": "male",
    "P2764": "female",
    "P1031": "male",
    "P1209": "male",
    "P1256": "male",
    "P1366": "male",
    "P1275": "female",
    "P1198": "male",
    "P1535": "female",
    "P1146": "male",
    "P1534": "female",
    "P1216": "female",
    "P1741": "male",
    "P1019": "male",
    "P1932": "male",
    "P1699": "male",
    "P1411": "male",
    "P1422": "male",
    "P1464": "female",
    "P1923": "male",
    "P1600": "female",
    "P1306": "male",
    "P1611": "male",
    "P2223": "male",
    "P2201": "female",
    "P1871": "female",
    "P1989": "female",
    "P1018": "male",
    "P2028": "female",
    "P2055": "male",
    "P2088": "female",
    "P2024": "male",
    "P2132": "male",
    "P2085": "male",
    "P2112": "male",
    "P1404": "female",
    "P2045": "male",
    "P2466": "male",
    "P2404": "female",
    "P2061": "male",
    "P2130": "male",
    "P2142": "male",
    "P1993": "male",
    "P2476": "female",
    "P2468": "male",
    "P2713": "female",
    "P3740": "female",
    "P2013": "male",
    "P3230": "male",
    "P3218": "male",
    "P3095": "male",
    "P2462": "male",
    "P3206": "male",
    "P2012": "male",
    "P3657": "male",
    "P3241": "male",
    "P2152": "female",
    "P3671": "male",
    "P3506": "male",
    "P3487": "male",
    "P3485": "male",
    "P1938": "male",
    "P3603": "male",
    "P3100": "male",
    "P3208": "female",
    "P3716": "male",
    "P3821": "male",
    "P3882": "male",
    "P3851": "male",
    "P3750": "male",
    "P4116": "male",
    "P3658": "female",
    "P4059": "female",
    "P4057": "male",
    "P1429": "female",
    "P3498": "male",
    "P1773": "male",
    "P4040": "male",
    "P3810": "female",
    "P2947": "male",
    "P3964": "female",
    "P3669": "male",
    "P3520": "male",
    "P3641": "female",
    "P3676": "female",
    "P3675": "male",
    "P4130": "female",
    "P4048": "female",
    "P3792": "female",
    "P3510": "male",
    "P4066": "male",
    "P3796": "female",
    "P4178": "male",
    "P4133": "male",
    "P3928": "female",
    "P4166": "male",
    "P4144": "male",
    "P4364": "male",
    "P4354": "male",
    "P4173": "male",
    "P3969": "male",
    "P4353": "male",
    "P4203": "male",
    "P4174": "male",
    "P4391": "male",
    "P4037": "male",
    "P4176": "female",
    "P4365": "female",
    "P4221": "female",
    "P4828": "male",
    "P4938": "male",
    "P1290": "female",
    "P4351": "female",
    "P4677": "male",
    "P3732": "female",
    "P4821": "male",
    "P4357": "female",
    "P3025": "male",
    "P4366": "male",
    "P4214": "female",
    "P4683": "female",
    "P4779": "male",
    "P4726": "male",
    "P3921": "male",
    "P5143": "female",
    "P3264": "male",
    "P2479": "male",
    "P4685": "male",
    "P2967": "male",
    "P4300": "male",
    "P1982": "female",
    "P2974": "female",
    "P4712": "male",
    "P4827": "male",
    "P5018": "male",
    "P4972": "male",
    "P5047": "male",
    "P3932": "male",
    "P1431": "male",
    "P0217": "male",
    "P0350": "female",
    "P0351": "male",
    "P0665": "female",
    "P0671": "male",
    "P0467": "male",
    "P0779": "female",
    "P0840": "female",
    "P0116": "female",
    "P0466": "male",
    "P0484": "male",
    "P0485": "female",
    "P0663": "male",
    "P0697": "female",
    "P0780": "female",
    "P0216": "female",
    "P0566": "male",
    "P0660": "male",
    "P0696": "male",
    "P0410": "female",
    "P1020": "female",
    "P0672": "female",
    "P0959": "male",
    "P0879": "male",
    "P0370": "male",
    "P1041": "male",
    "P1362": "male",
    "P1500": "female",
    "P1604": "female",
    "P2284": "male",
    "P2283": "male",
    "P2761": "male",
    "P1891": "male",
    "P1203": "female",
    "P1356": "female",
    "P1409": "male",
    "P5042": "female",
    "P5062": "female",
    "P1067": "female",
    "P1076": "male",
    "P1112": "male",
    "P1289": "female",
    "P1917": "female",
    "P5063": "male",
    "P1174": "male",
    "P1357": "male",
    "P2279": "female",
    "P1066": "female",
    "P1113": "male",
    "P1363": "female",
    "P5043": "female",
    "P1040": "male",
    "P1204": "female",
    "P1603": "female",
    "P1599": "female",
    "P3430": "male",
    "P4590": "female",
    "P4768": "male",
    "P2768": "female",
    "P1659": "female",
    "P3730": "female",
    "P3836": "male",
    "P3837": "male",
    "P5265": "female",
    "P2614": "male",
    "P1736": "female",
    "P5154": "male",
    "P5155": "male",
    "P3431": "female",
    "P4591": "male",
    "P5628": "female",
    "P3779": "male",
    "P2966": "female",
    "P1662": "male",
    "P3731": "male",
    "P3778": "male",
    "P5629": "female",
    "P0045": "female",
    "P0051": "female",
    "P0053": "male",
    "P0055": "female",
    "P0072": "male",
    "P0076": "female",
    "P0096": "male",
    "P0046": "male",
    "P0049": "male",
    "P0054": "female",
    "P0078": "female",
    "P0077": "male",
    "P0080": "male",
    "P0081": "male",
    "P0048": "female",
    "P0056": "female",
    "P0057": "female",
    "P0083": "male",
    "P0095": "male",
    "P0052": "female",
    "P0082": "female",
    "P0071": "female",
    "P0094": "male",
    "P0098": "male",
    "P0112": "female",
    "P0125": "male",
    "P0126": "female",
    "P0141": "male",
    "P0142": "male",
    "P0146": "female",
    "P0149": "female",
    "P0099": "male",
    "P0100": "female",
    "P0113": "female",
    "P0119": "male",
    "P0124": "female",
    "P0139": "female",
    "P0097": "female",
    "P0104": "male",
    "P0138": "female",
    "P0101": "female",
    "P0118": "male",
    "P0135": "female",
    "P0140": "female",
    "P0143": "male",
    "P0147": "male",
    "P0117": "female",
    "P0148": "female",
    "P0121": "male",
    "P0158": "female",
    "P0159": "female",
    "P0160": "female",
    "P0163": "female",
    "P0169": "male",
    "P0171": "female",
    "P0176": "male",
    "P0200": "male",
    "P0201": "male",
    "P0042": "female",
    "P0161": "male",
    "P0167": "male",
    "P0172": "female",
    "P0180": "female",
    "P0183": "female",
    "P0205": "male",
    "P0166": "male",
    "P0174": "male",
    "P0177": "male",
    "P0162": "female",
    "P0008": "female",
    "P0175": "male",
    "P0165": "male",
    "P0170": "female",
    "P0173": "male",
    "P0168": "male",
    "P0178": "male",
    "P0206": "male",
    "P0164": "male",
    "P0184": "female",
    "P0207": "female",
    "P0214": "female",
    "P0215": "female",
    "P0241": "female",
    "P0244": "male",
    "P0209": "male",
    "P0219": "male",
    "P0226": "male",
    "P0227": "female",
    "P0250": "female",
    "P0001": "male",
    "P0243": "female",
    "P0212": "female",
    "P0224": "female",
    "P0239": "female",
    "P0242": "male",
    "P0213": "female",
    "P0220": "female",
    "P0221": "female",
    "P0210": "male",
    "P0225": "male",
    "P0246": "female",
    "P0208": "male",
    "P0211": "male",
    "P0218": "female",
    "P0245": "male",
    "P0247": "female",
    "P0253": "male",
    "P0255": "male",
    "P0278": "male",
    "P0280": "female",
    "P0283": "male",
    "P0284": "male",
    "P0286": "female",
    "P0249": "female",
    "P0248": "female",
    "P0252": "male",
    "P0260": "female",
    "P0285": "male",
    "P0281": "female",
    "P0256": "female",
    "P0254": "female",
    "P0288": "male",
    "P0287": "male",
    "P0277": "female",
    "P0258": "male",
    "P0290": "male",
    "P0251": "male",
    "P0289": "male",
    "P0297": "male",
    "P0304": "male",
    "P0307": "male",
    "P0306": "male",
    "P0330": "female",
    "P0333": "male",
    "P0336": "female",
    "P0292": "female",
    "P0299": "male",
    "P0311": "female",
    "P0328": "female",
    "P0334": "female",
    "P0295": "female",
    "P0337": "male",
    "P0338": "male",
    "P0302": "male",
    "P0305": "male",
    "P0309": "female",
    "P0331": "male",
    "P0335": "female",
    "P0291": "female",
    "P0294": "female",
    "P0298": "female",
    "P0301": "female",
    "P0303": "male",
    "P0296": "male",
    "P0293": "male",
    "P0329": "female",
    "P0339": "female",
    "P0308": "female",
    "P0344": "female",
    "P0346": "female",
    "P0375": "female",
    "P0379": "female",
    "P0384": "female",
    "P0345": "male",
    "P0353": "female",
    "P0376": "male",
    "P0354": "female",
    "P0347": "male",
    "P0349": "male",
    "P0352": "female",
    "P0374": "female",
    "P0341": "female",
    "P0340": "male",
    "P0373": "male",
    "P0342": "male",
    "P0343": "male",
    "P0372": "female",
    "P0385": "female",
    "P0378": "female",
    "P0390": "male",
    "P0411": "female",
    "P0415": "female",
    "P0417": "male",
    "P0418": "female",
    "P0425": "male",
    "P0428": "female",
    "P0388": "female",
    "P0391": "female",
    "P0386": "female",
    "P0387": "female",
    "P0406": "male",
    "P0420": "female",
    "P0423": "male",
    "P0392": "male",
    "P0393": "male",
    "P0412": "male",
    "P0413": "male",
    "P0416": "male",
    "P0405": "male",
    "P0427": "female",
    "P0419": "female",
    "P0433": "male",
    "P0424": "male",
    "P0440": "female",
    "P0441": "female",
    "P0446": "female",
    "P0461": "female",
    "P0430": "male",
    "P0431": "male",
    "P0429": "male",
    "P0452": "female",
    "P0455": "female",
    "P0459": "female",
    "P0432": "male",
    "P0445": "female",
    "P0453": "female",
    "P0439": "male",
    "P0434": "male",
    "P0437": "female",
    "P0458": "male",
    "P0435": "female",
    "P0438": "female",
    "P0447": "male",
    "P0456": "male",
    "P0463": "female",
    "P0436": "female",
    "P0462": "female",
    "P0457": "female",
    "P0464": "male",
    "P0468": "female",
    "P0471": "female",
    "P0482": "female",
    "P0474": "male",
    "P0475": "male",
    "P0478": "male",
    "P0491": "female",
    "P0502": "female",
    "P0483": "female",
    "P0024": "male",
    "P0480": "male",
    "P0465": "male",
    "P0501": "male",
    "P0472": "male",
    "P0481": "male",
    "P0473": "female",
    "P0477": "female",
    "P0479": "female",
    "P0496": "female",
    "P0504": "female",
    "P0503": "male",
    "P0509": "male",
    "P0511": "male",
    "P0513": "male",
    "P0514": "female",
    "P0525": "female",
    "P0527": "male",
    "P0531": "female",
    "P0528": "male",
    "P0515": "female",
    "P0517": "female",
    "P0516": "male",
    "P0518": "female",
    "P0530": "female",
    "P0013": "male",
    "P0505": "male",
    "P0507": "male",
    "P0519": "male",
    "P0520": "female",
    "P0512": "female",
    "P0521": "female",
    "P0510": "male",
    "P0523": "male",
    "P0526": "male",
    "P0522": "male",
    "P0529": "female",
    "P0536": "male",
    "P0535": "female",
    "P0547": "female",
    "P0558": "female",
    "P0560": "female",
    "P0567": "male",
    "P0572": "male",
    "P0578": "female",
    "P0537": "male",
    "P0542": "female",
    "P0545": "female",
    "P0551": "female",
    "P0550": "female",
    "P0557": "male",
    "P0538": "male",
    "P0555": "female",
    "P0559": "female",
    "P0544": "female",
    "P0554": "female",
    "P0583": "female",
    "P0541": "female",
    "P0563": "female",
    "P0568": "female",
    "P0552": "male",
    "P0548": "female",
    "P0579": "male",
    "P0543": "male",
    "P0556": "female",
    "P0584": "male",
    "P0549": "male",
    "P0540": "female",
    "P0585": "male",
    "P0590": "male",
    "P0594": "male",
    "P0605": "female",
    "P0609": "female",
    "P0610": "female",
    "P0591": "female",
    "P0596": "male",
    "P0595": "female",
    "P0598": "male",
    "P0604": "male",
    "P0603": "female",
    "P0607": "female",
    "P0599": "female",
    "P0586": "male",
    "P0588": "female",
    "P0592": "male",
    "P0597": "male",
    "P0606": "female",
    "P0608": "female",
    "P0593": "female",
    "P0600": "female",
    "P0602": "female",
    "P0589": "male",
    "P0612": "female",
    "P0620": "male",
    "P0635": "female",
    "P0639": "female",
    "P0640": "female",
    "P0643": "female",
    "P0613": "female",
    "P0619": "male",
    "P0633": "female",
    "P0638": "male",
    "P0644": "male",
    "P0611": "female",
    "P0632": "female",
    "P0634": "male",
    "P0637": "female",
    "P0645": "female",
    "P0614": "male",
    "P0628": "female",
    "P0636": "male",
    "P0642": "female",
    "P0624": "female",
    "P0630": "male",
    "P0631": "male",
    "P0616": "male",
    "P0641": "female",
    "P0617": "male",
    "P0629": "male",
    "P0650": "male",
    "P0652": "female",
    "P0667": "male",
    "P0666": "female",
    "P0647": "female",
    "P0653": "female",
    "P0669": "female",
    "P0670": "female",
    "P0674": "female",
    "P0679": "male",
    "P0649": "female",
    "P0668": "male",
    "P0651": "male",
    "P0677": "female",
    "P0648": "male",
    "P0673": "female",
    "P0656": "male",
    "P0646": "female",
    "P0661": "male",
    "P0664": "male",
    "P0657": "female",
    "P0654": "male",
    "P0701": "male",
    "P0704": "male",
    "P0711": "male",
    "P0675": "female",
    "P0699": "male",
    "P0709": "male",
    "P0685": "male",
    "P0689": "male",
    "P0688": "male",
    "P0700": "male",
    "P0684": "male",
    "P0693": "male",
    "P0706": "female",
    "P0703": "female",
    "P0698": "female",
    "P0712": "female",
    "P0714": "male",
    "P0705": "male",
    "P0715": "female",
    "P0713": "female",
    "P0717": "male",
    "P0723": "male",
    "P0724": "female",
    "P0727": "female",
    "P0735": "female",
    "P0720": "female",
    "P0722": "male",
    "P0730": "female",
    "P0738": "male",
    "P0718": "female",
    "P0726": "male",
    "P0729": "female",
    "P0736": "female",
    "P0719": "male",
    "P0725": "female",
    "P0734": "female",
    "P0716": "male",
    "P0733": "male",
    "P0732": "male",
    "P0721": "female",
    "P0741": "female",
    "P0745": "female",
    "P0748": "female",
    "P0751": "male",
    "P0753": "female",
    "P0757": "female",
    "P0758": "female",
    "P0763": "female",
    "P0768": "female",
    "P0766": "female",
    "P0771": "female",
    "P0755": "female",
    "P0747": "male",
    "P0767": "female",
    "P0750": "male",
    "P0754": "female",
    "P0756": "male",
    "P0772": "female",
    "P0749": "male",
    "P0746": "female",
    "P0752": "female",
    "P0770": "male",
    "P0759": "male",
    "P0769": "female",
    "P0762": "female",
    "P0773": "female",
    "P0775": "female",
    "P0777": "male",
    "P0781": "male",
    "P0778": "female",
    "P0783": "male",
    "P0786": "female",
    "P0782": "female",
    "P0787": "female",
    "P0793": "male",
    "P0774": "male",
    "P0784": "female",
    "P0788": "female",
    "P0790": "male",
    "P0795": "male",
    "P0796": "male",
    "P0776": "female",
    "P0797": "male",
    "P0792": "female",
    "P0785": "female",
    "P0814": "female",
    "P0812": "male",
    "P0824": "male",
    "P0836": "male",
    "P0841": "male",
    "P0838": "female",
    "P0810": "male",
    "P0804": "female",
    "P0813": "male",
    "P0819": "male",
    "P0809": "female",
    "P0811": "female",
    "P0820": "female",
    "P0834": "female",
    "P0837": "female",
    "P0828": "female",
    "P0803": "female",
    "P0818": "male",
    "P0808": "female",
    "P0821": "male",
    "P0839": "female",
    "P0807": "female",
    "P0815": "female",
    "P0842": "male",
    "P0846": "female",
    "P0849": "male",
    "P0866": "male",
    "P0873": "female",
    "P0876": "male",
    "P0877": "female",
    "P0878": "male",
    "P0857": "male",
    "P0853": "female",
    "P0864": "female",
    "P0863": "female",
    "P0850": "female",
    "P0859A": "male",
    "P0855": "male",
    "P0871": "male",
    "P0854": "female",
    "P0848": "female",
    "P0856": "female",
    "P0858": "male",
    "P0872": "male",
    "P0875": "female",
    "P0874": "female",
    "P0843": "male",
    "P0883": "female",
    "P0884": "female",
    "P0888": "female",
    "P0890": "female",
    "P0899": "female",
    "P0907": "female",
    "P0910": "female",
    "P0911": "male",
    "P0882": "female",
    "P0887": "female",
    "P0885": "male",
    "P0897": "female",
    "P0904": "male",
    "P0912": "male",
    "P0881": "male",
    "P0891": "female",
    "P0889": "female",
    "P0900": "male",
    "P0898": "female",
    "P0908": "female",
    "P0913": "female",
    "P0886": "female",
    "P0892": "male",
    "P0901": "female",
    "P0905": "male",
    "P0915": "male",
    "P0918": "female",
    "P0923": "female",
    "P0936": "male",
    "P0954": "female",
    "P0926": "male",
    "P0941": "female",
    "P0945": "male",
    "P0951": "female",
    "P0952": "female",
    "P0917": "female",
    "P0953": "male",
    "P0942": "female",
    "P0916": "female",
    "P0931": "female",
    "P0957": "female",
    "P0922": "female",
    "P0944": "male",
    "P0914": "female",
    "P0932": "male",
    "P0943": "male",
    "P0956": "male",
    "P0972": "male",
    "P0981": "female",
    "P0988": "female",
    "P0963": "female",
    "P0993": "female",
    "P0995": "female",
    "P0979": "male",
    "P0409": "female",
    "P0968": "female",
    "P0992": "male",
    "P0961": "female",
    "P0960": "female",
    "P0971": "female",
    "P0987": "male",
    "P0982": "female",
    "P0962": "male",
    "P0844": "male",
    "P1027": "male",
    "P1037": "female",
    "P1012": "female",
    "P1024": "female",
    "P1030": "male",
    "P1035": "female",
    "P1032": "male",
    "P1013": "female",
    "P1029": "male",
    "P1034": "female",
    "P1028": "male",
    "P1039": "female",
    "P1043": "male",
    "P1046": "male",
    "P1051": "female",
    "P1058": "male",
    "P1059": "male",
    "P1080": "male",
    "P1045": "female",
    "P1055": "female",
    "P1057": "female",
    "P1060": "male",
    "P1065": "male",
    "P1056": "female",
    "P1071": "male",
    "P1053": "female",
    "P1070": "male",
    "P1077": "male",
    "P1078": "male",
    "P1044": "female",
    "P1052": "male",
    "P1079": "female",
    "P1072": "female",
    "P1064": "female",
    "P1082": "female",
    "P1054": "male",
    "P1081": "female",
    "P1097": "male",
    "P1098": "male",
    "P1109": "male",
    "P1085": "female",
    "P1086": "male",
    "P1087": "male",
    "P0859": "male",
    "P1083": "male",
    "P1093": "female",
    "P1096": "male",
    "P1090": "male",
    "P1091": "male",
    "P1095": "male",
    "P1110": "female",
    "P1120": "male",
    "P1107": "male",
    "P1105": "male",
    "P1092": "female",
    "P1108": "male",
    "P1111": "male",
    "P1122": "female",
    "P1121": "male",
    "P1128": "male",
    "P1142": "female",
    "P1150": "female",
    "P1126": "male",
    "P1129": "male",
    "P1134": "male",
    "P1131": "male",
    "P1132": "female",
    "P1141": "female",
    "P1136": "female",
    "P1130": "male",
    "P1135": "male",
    "P1138": "female",
    "P1145": "male",
    "P1133": "female",
    "P1140": "female",
    "P1127": "female",
    "P1156": "female",
    "P1160": "male",
    "P1164": "male",
    "P1167": "female",
    "P1161": "female",
    "P1162": "male",
    "P1163": "male",
    "P1170": "female",
    "P1155": "male",
    "P1159A": "female",
    "P1166": "female",
    "P1158": "male",
    "P1153": "male",
    "P1169": "female",
    "P1165": "male",
    "P1168": "female",
    "P1157": "female",
    "P1172": "male",
    "P1193": "male",
    "P1171": "female",
    "P1192": "female",
    "P1179": "male",
    "P1187": "female",
    "P1173": "female",
    "P1189": "female",
    "P1178": "male",
    "P1175": "female",
    "P1188": "female",
    "P1185": "female",
    "P0017": "female",
    "P1207": "female",
    "P1201": "female",
    "P1205": "female",
    "P1202": "male",
    "P1200": "female",
    "P1211": "female",
    "P1208": "female",
    "P1206": "male",
    "P1199": "male",
    "P0279": "male",
    "P1197": "female",
    "P1196": "male",
    "P1221": "female",
    "P1217": "female",
    "P1222": "female",
    "P1225": "male",
    "P1220": "female",
    "P1224": "male",
    "P1223": "male",
    "P1241": "male",
    "P1245": "male",
    "P1255": "female",
    "P1237": "female",
    "P1235": "male",
    "P1236": "female",
    "P1238": "female",
    "P1244": "female",
    "P1242": "male",
    "P1234": "female",
    "P1068": "female",
    "P1073": "female",
    "P1249": "female",
    "P1084": "female",
    "P1094": "female",
    "P1069": "female",
    "P1252": "male",
    "P1253": "male",
    "P1139": "male",
    "P1149": "female",
    "P1151": "female",
    "P1152": "female",
    "P1117": "female",
    "P1148": "female",
    "P1116": "female",
    "P1154": "female",
    "P1159": "female",
    "P1250": "female",
    "P1257": "female",
    "P1276": "female",
    "P1277": "female",
    "P1280": "female",
    "P1281": "male",
    "P1285": "male",
    "P1292": "female",
    "P1291": "male",
    "P1293": "female",
    "P1268": "female",
    "P1273": "female",
    "P1279": "male",
    "P1282": "female",
    "P1286": "female",
    "P1260": "male",
    "P1278": "male",
    "P1259": "female",
    "P1262": "male",
    "P1294": "female",
    "P1258": "female",
    "P1269": "male",
    "P1261": "male",
    "P1300": "female",
    "P1358": "male",
    "P1361": "female",
    "P1367": "female",
    "P1379": "female",
    "P1378": "male",
    "P1384": "female",
    "P1385": "female",
    "P1360": "female",
    "P1375": "female",
    "P1374": "female",
    "P1376": "female",
    "P1382": "male",
    "P1383": "female",
    "P1369": "male",
    "P1386": "female",
    "P1377": "male",
    "P1393": "female",
    "P1372": "female",
    "P1380": "male",
    "P1381": "male",
    "P1359": "male",
    "P1365": "female",
    "P1368": "male",
    "P1373": "male",
    "P1301": "male",
    "P1387": "male",
    "P1364": "male",
    "P1399": "female",
    "P1403": "female",
    "P1407": "male",
    "P1562": "male",
    "P1579": "male",
    "P1582": "female",
    "P1591": "male",
    "P1395": "female",
    "P1559": "male",
    "P1563": "male",
    "P1580": "female",
    "P1588": "female",
    "P1590": "male",
    "P1394": "female",
    "P1401": "female",
    "P1586": "male",
    "P1585": "female",
    "P1402": "female",
    "P1584": "female",
    "P1398": "female",
    "P1408": "male",
    "P1593": "male",
    "P1589": "male",
    "P1592": "male",
    "P1558": "male",
    "P1583": "male",
    "P1587": "female",
    "P1594": "male",
    "P1581": "male",
    "P1595": "female",
    "P1598": "female",
    "P1665": "female",
    "P1670": "male",
    "P1674": "female",
    "P1673": "female",
    "P1675": "male",
    "P1661": "male",
    "P1663": "male",
    "P1664": "female",
    "P1666": "female",
    "P1667": "male",
    "P1671": "female",
    "P1672": "female",
    "P1602": "female",
    "P1668": "female",
    "P1669": "female",
    "P1605": "male",
    "P1660": "female",
    "P1597": "male",
    "P1601": "female",
    "P1658": "female",
    "P1913": "male",
    "P2311": "female",
    "P2379": "female",
    "P2380": "male",
    "P2381": "male",
    "P2413": "female",
    "P2427": "male",
    "P2438": "female",
    "P2285": "female",
    "P2382": "male",
    "P2204": "male",
    "P2416": "female",
    "P2429": "female",
    "P2304": "female",
    "P2310": "male",
    "P2415": "female",
    "P2426": "male",
    "P2428": "female",
    "P2286": "male",
    "P2439": "male",
    "P2303": "male",
    "P2305": "female",
    "P2306": "female",
    "P2282": "female",
    "P2383": "female",
    "P2437": "female",
    "P2421": "female",
    "P2414": "female",
    "P2522": "female",
    "P2554": "female",
    "P2556": "male",
    "P2523": "female",
    "P2535": "female",
    "P2537": "female",
    "P2539": "female",
    "P2532": "female",
    "P2536": "male",
    "P2538": "female",
    "P2546": "female",
    "P2545": "female",
    "P2555": "male",
    "P2558": "female",
    "P2527": "male",
    "P2560": "female",
    "P2557": "female",
    "P2540": "female",
    "P2542": "female",
    "P2531": "male",
    "P2541": "male",
    "P2567": "male",
    "P2528": "female",
    "P2559": "female",
    "P2549": "female",
    "P2568": "male",
    "P2550": "male",
    "P2754": "female",
    "P2074": "female",
    "P2010": "male",
    "P4010": "male",
    "P4024": "male",
    "P4001": "male",
    "P4031": "male",
    "P2762": "female",
    "P2770": "male",
    "P2772": "female",
    "P4025": "male",
    "P4018": "female",
    "P4032": "male",
    "P4028": "male",
    "P4022": "female",
    "P4029": "male",
    "P2755": "male",
    "P2771": "male",
    "P4023": "female",
    "P2757": "male",
    "P4017": "male",
    "P2758": "female",
    "P4041": "female",
    "P4036": "female",
    "P4046": "female",
    "P4042": "male",
    "P4034": "male",
    "P4038": "male",
    "P4047": "female",
    "P4043": "female",
    "P4035": "male",
    "P4050": "female",
    "P4053": "female",
    "P4027": "male",
    "P4054": "male",
    "P4049": "male",
    "P4052": "male",
    "P4058": "female",
    "P4056": "female",
    "P4014": "female",
    "P4055": "male",
    "P4060": "female",
    "P4062": "male",
    "P4063": "female",
    "P4061": "male",
    "P4002": "female",
    "P4065": "male",
    "P4033": "male",
    "P4064": "male",
    "P4067": "female",
    "P4069": "male",
    "P4068": "female",
    "P4070": "female",
    "P4021": "male",
    "P4072": "female",
    "P4026": "female",
    "P4015": "female",
    "P4073": "female",
    "P4074": "male",
    "P4075": "female",
    "P4071": "female",
    "P4077": "male",
    "P4076": "male",
    "P4078": "female",
    "P4082": "male",
    "P4084": "male",
    "P4085": "male",
    "P4079": "male",
    "P4080": "male",
    "P4083": "female",
    "P4081": "female",
    "P4086": "male",
    "P4090": "male",
    "P4088": "female",
    "P4087": "female",
    "P4091": "female",
    "P4089": "male",
    "P4092": "female",
    "P4093": "female",
    "P4097": "female",
    "P4096": "male",
    "P4095": "female",
    "P4094": "male",
    "P4098": "male",
    "P4099": "male",
    "P4009": "male",
    "P4106": "female",
    "P4101": "female",
    "P4103": "female",
    "P4102": "male",
    "P4100": "female",
    "P4107": "female",
    "P4008": "male",
    "P4110": "male",
    "P4109": "male",
    "P4108": "male",
    "P4111": "female",
    "P4112": "male",
    "P4114": "male",
    "P4121": "male",
    "P4122": "male",
    "P4123": "male",
    "P4120": "male",
    "P4113": "male",
    "P4117": "male",
    "P4126": "male",
    "P4118": "male",
    "P4124": "female",
    "P4119": "male",
    "P4115": "male",
    "P4127": "female",
    "P4129": "male",
    "P4125": "male",
    "P4131": "male",
    "P4134": "female",
    "P4135": "female",
    "P4132": "female",
    "P4128": "female",
    "P4141": "female",
    "P4137": "female",
    "P4138": "male",
    "P4136": "female",
    "P4142": "female",
    "P4140": "female",
    "P4145": "male",
    "P4146": "male",
    "P4143": "female",
    "P4148": "male",
    "P4150": "male",
    "P4154": "male",
    "P4155": "female",
    "P4151": "female",
    "P4152": "female",
    "P4153": "male",
    "P4157": "male",
    "P4147": "male",
    "P4149": "male",
    "P4156": "female",
    "P4161": "female",
    "P4162": "male",
    "P4159": "female",
    "P4160": "male",
    "P4164": "female",
    "P4167": "female",
    "P4170": "female",
    "P4169": "female",
    "P4165": "male",
    "P4168": "female",
    "P4171": "male",
    "P4172": "male",
    "P4175": "female",
    "P4180": "female",
    "P4181": "female",
    "P4177": "female",
    "P4179": "female",
    "P4185": "male",
    "P4183": "male",
    "P4182": "male",
    "P4184": "male",
    "P4186": "male",
    "P4187": "male",
    "P4188": "male",
    "P4189": "female",
    "P4191": "female",
    "P4192": "female",
    "P4194": "male",
    "P4193": "male",
    "P4190": "female",
    "P4195": "female",
    "P4196": "male",
    "P4198": "male",
    "P4199": "female",
    "P4197": "female",
    "P4231": "female",
    "P4202": "male",
    "P4200": "male",
    "P4201": "male",
    "P4240": "female",
    "P4205": "male",
    "P4206": "male",
    "P4204": "male",
    "P4208": "female",
    "P4210": "male",
    "P4211": "male",
    "P4207": "male",
    "P4213": "male",
    "P4209": "female",
    "P4212": "male",
    "P4218": "female",
    "P4219": "male",
    "P4215": "male",
    "P4217": "male",
    "P4220": "male",
    "P4216": "male",
    "P4222": "female",
    "P4223": "female",
    "P4224": "female",
    "P4225": "female",
    "P4227": "male",
    "P4228": "male",
    "P4229": "female",
    "P4226": "male",
    "P4234": "female",
    "P4230": "female",
    "P4233": "female",
    "P4232": "female",
    "P4236": "male",
    "P4238": "male",
    "P4241": "female",
    "P4237": "female",
    "P4239": "female",
    "P4242": "male",
    "P4243": "female",
    "P4245": "female",
    "P4247": "female",
    "P4244": "male",
    "P4246": "female",
    "P4249": "male",
    "P4251": "female",
    "P4250": "female",
    "P4252": "female",
    "P4253": "female",
    "P4256": "female",
    "P4254": "female",
    "P4259": "female",
    "P4260": "female",
    "P4257": "female",
    "P4258": "male",
    "P4255": "female",
    "P4261": "female",
    "P4262": "female",
    "P4263": "male",
    "P4265": "female",
    "P4264": "female",
    "P4267": "female",
    "P4268": "female",
    "P4266": "female",
    "P5005": "female",
    "P5011": "male",
    "P5013": "male",
    "P5012": "female",
    "P5002": "male",
    "P5010": "female",
    "P5014": "female",
    "P5017": "female",
    "P5019": "male",
    "P5020": "male",
    "P5009": "male",
    "P5015": "male",
    "P5016": "male",
    "P5001": "male",
    "P5008": "male",
    "P5007": "male",
    "P5006": "female",
    "P5022": "female",
    "P5024": "male",
    "P5027": "female",
    "P5032": "female",
    "P5026": "female",
    "P5025": "male",
    "P5028": "male",
    "P5033": "female",
    "P5034": "male",
    "P5021": "female",
    "P5029": "male",
    "P5023": "female",
    "P5035": "female",
    "P5045": "male",
    "P5044": "male",
    "P5046": "male",
    "P5048": "female",
    "P5050": "male",
    "P5040": "female",
    "P5041": "male",
    "P5049": "female",
    "P5036": "female",
    "P5037": "male",
    "P5051": "male",
    "P5052": "female",
    "P5053": "female",
    "P5058": "male",
    "P5066": "female",
    "P5071": "female",
    "P5072": "male",
    "P5056": "male",
    "P5057": "male",
    "P5065": "female",
    "P5064": "female",
    "P5067": "female",
    "P5068": "male",
    "P5059": "male",
    "P5073": "female",
    "P5078": "female",
    "P5084": "male",
    "P5091": "female",
    "P5094": "female",
    "P5093": "female",
    "P5096": "female",
    "P5098": "male",
    "P5099": "female",
    "P5077": "male",
    "P5085": "female",
    "P5086": "male",
    "P5087": "male",
    "P5088": "male",
    "P5090": "female",
    "P5076": "male",
    "P5080": "female",
    "P5083": "female",
    "P5092": "female",
    "P5097": "female",
    "P5100": "male",
    "P5079": "female",
    "P5095": "female",
    "P5089": "female",
    "P5101": "male",
    "P5103": "female",
    "P5109": "male",
    "P5108": "female",
    "P5110": "male",
    "P5105": "male",
    "P5116": "male",
    "P5106": "male",
    "P5115": "female",
    "P5107": "male",
    "P5112": "female",
    "P5113": "female",
    "P5102": "male",
    "P5117": "female",
    "P5111": "male",
    "P5114": "male",
    "P5121": "male",
    "P5127": "male",
    "P5129": "female",
    "P5131": "female",
    "P5130": "male",
    "P5132": "female",
    "P5122": "male",
    "P5135": "female",
    "P5120": "male",
    "P5126": "male",
    "P5133": "female",
    "P5137": "female",
    "P5136": "female",
    "P5118": "female",
    "P5134": "female",
    "P5123": "female",
    "P5128": "female",
    "P5138": "male",
    "P5141": "female",
    "P5144": "male",
    "P5148": "male",
    "P5157": "male",
    "P5159": "male",
    "P5139": "male",
    "P5142": "male",
    "P5151": "female",
    "P5152": "male",
    "P5153": "male",
    "P5156": "male",
    "P5140": "male",
    "P5150": "female",
    "P5160": "female",
    "P5146": "male",
    "P5149": "female",
    "P5147": "male",
    "P5162": "female",
    "P5161": "female",
    "P5167": "female",
    "P5172": "male",
    "P5170": "female",
    "P5173": "female",
    "P5175": "male",
    "P5177": "male",
    "P5163": "male",
    "P5164": "male",
    "P5166": "male",
    "P5158": "female",
    "P5165": "female",
    "P5168": "male",
    "P5169": "female",
    "P5171": "female",
    "P5174": "female",
    "P5178": "male",
    "P5180": "male",
    "P5184": "female",
    "P5185": "female",
    "P5183": "male",
    "P5186": "female",
    "P5188": "female",
    "P5193": "female",
    "P5187": "female",
    "P5190": "male",
    "P5179": "male",
    "P5182": "male",
    "P5189": "male",
    "P5194": "male",
    "P5181": "male",
    "P5195": "female",
    "P5205": "male",
    "P5200": "male",
    "P5201": "female",
    "P5197": "male",
    "P5202": "male",
    "P5199": "female",
    "P5203": "male",
    "P5206": "male",
    "P5196": "male",
    "P5198": "male",
    "P5208": "male",
    "P5209": "female",
    "P5210": "female",
    "P5212": "male",
    "P5213": "male",
    "P5214": "male",
    "P5207": "female",
    "P5211": "male",
    "P5221": "female",
    "P5222": "female",
    "P5224": "female",
    "P5218": "male",
    "P5217": "female",
    "P5225": "female",
    "P5226": "male",
    "P5215": "female",
    "P5216": "male",
    "P5220": "male",
    "P5219": "female",
    "P5223": "male",
    "P5227": "male",
    "P5229": "female",
    "P5231": "female",
    "P5232": "male",
    "P5234": "female",
    "P5228": "male",
    "P5230": "female",
    "P5233": "male",
    "P5235": "female",
    "P5236": "male",
    "P5240": "female",
    "P5242": "male",
    "P5241": "female",
    "P5243": "male",
    "P5244": "male",
    "P5238": "male",
    "P5239": "female",
    "P5237": "female",
    "P5245": "female",
    "P5250": "female",
    "P5246": "male",
    "P5247": "male",
    "P5249": "male",
    "P5248": "male",
    "P5252": "female",
    "P5254": "female",
    "P5258": "male",
    "P5261": "female",
    "P5251": "male",
    "P5253": "male",
    "P5255": "female",
    "P5259": "female",
    "P5257": "male",
    "P5256": "female",
    "P5260": "female",
    "P5263": "female",
    "P5262": "female",
    "P5268": "female",
    "P5264": "female",
    "P5269": "male",
    "P5270": "male",
    "P5274": "female",
    "P5277": "male",
    "P5276": "female",
    "P5271": "male",
    "P5273": "female",
    "P5275": "female",
    "P5272": "male",
    "P5278": "male",
    "P5279": "female",
    "P5280": "male",
    "P5284": "female",
    "P5281": "female",
    "P5282": "female",
    "P5283": "female",
    "P5285": "male",
    "P5286": "male",
    "P5287": "female",
    "P5288": "female",
    "P5294": "male",
    "P5293": "male",
    "P5289": "female",
    "P5291": "female",
    "P5290": "female",
    "P5292": "male",
    "P5506": "female",
    "P5512": "male",
    "P5514": "male",
    "P5511": "female",
    "P5703": "female",
    "P5704": "female",
    "P1103": "male",
    "P1021": "male",
    "P5513": "female",
    "P5517": "female",
    "P5505": "female",
    "P5508": "male",
    "P5507": "male",
    "P1270": "male",
    "P1284": "male",
    "P1347": "male",
    "P1324": "male",
    "P1336": "female",
    "P1342": "male",
    "P1346": "male",
    "P1340": "male",
    "P1354": "female",
    "P1370": "male",
    "P1371": "female",
    "P1390": "male",
    "P1417": "male",
    "P1449": "male",
    "P1433": "male",
    "P1430": "male",
    "P1450": "male",
    "P1400": "male",
    "P1425": "male",
    "P1432": "male",
    "P1416": "male",
    "P1421": "male",
    "P1427": "male",
    "P1475": "male",
    "P1482": "male",
    "P1486": "male",
    "P1489": "male",
    "P1488": "female",
    "P1524": "female",
    "P1452": "male",
    "P1547": "male",
    "P1428": "male",
    "P1460": "male",
    "P1483": "male",
    "P1556": "female",
    "P1453": "male",
    "P1480": "male",
    "P1487": "male",
    "P1546": "male",
    "P1474": "female",
    "P1557": "male",
    "P1540": "male",
    "P1550": "male",
    "P1576": "male",
    "P1457": "female",
    "P1456": "female",
    "P1542": "female",
    "P1477": "female",
    "P1619": "male",
    "P1463": "female",
    "P1701": "female",
    "P1447": "male",
    "P1490": "male",
    "P1688": "female",
    "P1446": "male",
    "P1687": "male",
    "P1648": "male",
    "P1765": "male",
    "P1943": "female",
    "P2110": "female",
    "P1501": "male",
    "P1770": "male",
    "P2111": "female",
    "P1960": "female",
    "P1879": "male",
    "P1880": "female",
    "P1961": "male",
    "P1884": "male",
    "P1881": "male",
    "P1955": "female",
    "P1703": "male",
    "P1423": "male",
    "P1900": "male",
    "P1945": "male",
    "P1901": "male",
    "P1912": "male",
    "P2189": "male",
    "P2161": "male",
    "P1893": "male",
    "P2169": "male",
    "P1953": "female",
    "P1896": "male",
    "P1897": "female",
    "P1898": "female",
    "P2160": "male",
    "P1892": "male",
    "P1927": "female",
    "P1921": "male",
    "P1911": "male",
    "P1937": "male",
    "P2027": "male",
    "P1732": "female",
    "P1819": "male",
    "P1823": "female",
    "P1734": "female",
    "P1818": "male",
    "P1822": "female",
    "P1974": "male",
    "P1983": "male",
    "P1977": "male",
    "P2235": "male",
    "P1814": "male",
    "P1969": "male",
    "P1821": "female",
    "P1976": "female",
    "P1820": "female",
    "P2234": "female",
    "P1738": "male",
    "P1647": "female",
    "P2173": "male",
    "P1984": "female",
    "P1991": "male",
    "P2069": "female",
    "P1987": "male",
    "P2096": "male",
    "P2033": "male",
    "P2078": "female",
    "P1985": "male",
    "P2097": "female",
    "P1986": "male",
    "P2083": "female",
    "P1990": "female",
    "P2104": "female",
    "P2082": "male",
    "P2165": "male",
    "P2105": "male",
    "P2353": "female",
    "P2197": "male",
    "P2196": "male",
    "P2226": "male",
    "P2214": "female",
    "P2233": "female",
    "P1794": "female",
    "P2315": "male",
    "P2350": "male",
    "P2194": "male",
    "P2307": "male",
    "P2206": "male",
    "P2193": "male",
    "P2180": "male",
    "P2171": "female",
    "P2365": "male",
    "P2053": "male",
    "P2122": "male",
    "P2191": "male",
    "P2065": "female",
    "P2126": "female",
    "P2067": "male",
    "P2114": "female",
    "P2100": "male",
    "P2184": "female",
    "P2091": "female",
    "P2103": "male",
    "P2199": "male",
    "P2102": "male",
    "P2127": "male",
    "P2060": "male",
    "P2072": "male",
    "P2064": "male",
    "P2066": "male",
    "P2062": "female",
    "P2190": "male",
    "P2063": "female",
    "P2185": "female",
    "P2059": "male",
    "P1930": "male",
    "P2253": "female",
    "P2036": "female",
    "P2037": "male",
    "P2257": "male",
    "P2268": "male",
    "P1459": "female",
    "P2269": "female",
    "P1965": "female",
    "P1458": "male",
    "P2256": "male",
    "P2259": "female",
    "P2219": "male",
    "P2137": "female",
    "P2231": "male",
    "P2292": "male",
    "P2075": "male",
    "P2146": "male",
    "P2242": "male",
    "P2433": "male",
    "P2298": "male",
    "P2302": "male",
    "P2243": "female",
    "P1916": "male",
    "P2000": "male",
    "P1905": "male",
    "P2301": "female",
    "P2500": "male",
    "P2015": "male",
    "P2004": "male",
    "P2369": "male",
    "P2458": "female",
    "P2485": "male",
    "P2003": "male",
    "P2461": "female",
    "P2014": "male",
    "P1915": "female",
    "P2459": "female",
    "P2512": "female",
    "P2513": "female",
    "P2371": "male",
    "P1996": "male",
    "P2483": "male",
    "P2484": "male",
    "P2474": "female",
    "P2153": "female",
    "P2507": "female",
    "P2148": "male",
    "P2149": "male",
    "P2478": "male",
    "P2465": "female",
    "P2787": "male",
    "P2254": "male",
    "P1914": "male",
    "P2195": "female",
    "P2707": "male",
    "P2294": "male",
    "P2295": "female",
    "P2517": "female",
    "P2446": "female",
    "P2530": "male",
    "P2515": "female",
    "P1941": "male",
    "P2520": "male",
    "P2457": "male",
    "P2289": "male",
    "P1957": "male",
    "P2786": "male",
    "P2529": "male",
    "P2448": "male",
    "P1972": "male",
    "P2514": "male",
    "P2276": "male",
    "P2330": "male",
    "P2333": "male",
    "P2157": "male",
    "P2320": "male",
    "P2051": "male",
    "P2182": "female",
    "P2317": "female",
    "P2325": "male",
    "P2336": "female",
    "P2007": "male",
    "P2316": "female",
    "P2337": "male",
    "P1964": "female",
    "P2001": "male",
    "P2827": "male",
    "P2318": "female",
    "P2342": "male",
    "P1971": "male",
    "P2903": "male",
    "P2341": "male",
    "P2900": "male",
    "P1496": "female",
    "P2456": "female",
    "P2901": "male",
    "P2819": "male",
    "P1720": "male",
    "P2095": "female",
    "P2340": "male",
    "P2390": "male",
    "P2905": "male",
    "P2825": "male",
    "P2452": "female",
    "P2920": "female",
    "P2608": "male",
    "P2869": "male",
    "P3040": "male",
    "P2453": "male",
    "P2969": "female",
    "P2921": "male",
    "P2728": "female",
    "P2907": "female",
    "P3038": "male",
    "P2860": "male",
    "P2475": "male",
    "P2215": "male",
    "P2629": "female",
    "P2644": "male",
    "P2868": "male",
    "P2929": "male",
    "P3043": "male",
    "P3086": "male",
    "P3067": "male",
    "P3079": "female",
    "P3078": "female",
    "P3088": "male",
    "P3085": "male",
    "P3084": "female",
    "P3076": "male",
    "P3087": "male",
    "P3045": "female",
    "P3065": "male",
    "P3075": "male",
    "P3092": "male",
    "P2747": "female",
    "P3044": "male",
    "P1906": "male",
    "P3082": "female",
    "P3074": "female",
    "P3077": "female",
    "P3083": "male",
    "P3103": "female",
    "P3108": "male",
    "P2693": "male",
    "P2709": "female",
    "P3109": "male",
    "P2630": "male",
    "P3163": "male",
    "P3170": "female",
    "P5528": "male",
    "P2225": "male",
    "P3125": "male",
    "P3149": "male",
    "P3161": "male",
    "P3168": "male",
    "P3169": "male",
    "P3171": "female",
    "P3146": "male",
    "P3154": "female",
    "P3148": "female",
    "P3855": "female",
    "P3173": "male",
    "P3156": "female",
    "P1491": "male",
    "P2224": "male",
    "P3147": "male",
    "P3152": "female",
    "P3119": "male",
    "P1575": "male",
    "P3295": "female",
    "P3334": "female",
    "P3335": "male",
    "P2442": "female",
    "P3250": "male",
    "P3336": "female",
    "P1753": "male",
    "P3323": "male",
    "P3324": "male",
    "P3265": "male",
    "P3331": "male",
    "P3296": "male",
    "P1877": "male",
    "P3317": "female",
    "P2880": "male",
    "P1860": "female",
    "P3330": "male",
    "P2884": "male",
    "P3003": "female",
    "P3326": "female",
    "P3249": "female",
    "P3322": "male",
    "P3325": "female",
    "P3337": "female",
    "P3342": "male",
    "P3353": "female",
    "P3352": "female",
    "P3318": "female",
    "P3345": "female",
    "P3361": "female",
    "P3338": "female",
    "P3349": "male",
    "P3355": "female",
    "P3364": "male",
    "P3370": "female",
    "P3360": "female",
    "P3362": "female",
    "P3350": "male",
    "P3354": "female",
    "P3368": "male",
    "P3369": "male",
    "P3344": "female",
    "P3346": "female",
    "P3340": "male",
    "P3339": "female",
    "P3375": "female",
    "P3341": "male",
    "P3374": "female",
    "P3377": "male",
    "P3376": "male",
    "P3379": "female",
    "P3381": "female",
    "P3380": "female",
    "P3383": "female",
    "P3385": "male",
    "P3382": "female",
    "P3391": "male",
    "P3432": "female",
    "P3392": "male",
    "P3117": "male",
    "P3110": "male",
    "P3390": "female",
    "P4864": "male",
    "P2791": "male",
    "P3200": "male",
    "P3393": "male",
    "P3384": "male",
    "P3389": "male",
    "P3204": "male",
    "P2464": "male",
    "P3388": "male",
    "P4872": "female",
    "P3225": "male",
    "P3232": "male",
    "P3233": "male",
    "P3007": "female",
    "P2943": "male",
    "P3280": "male",
    "P3289": "female",
    "P2641": "female",
    "P1497": "male",
    "P3234": "male",
    "P2879": "female",
    "P3237": "female",
    "P3276": "male",
    "P3306": "male",
    "P3235": "male",
    "P3303": "female",
    "P3298": "male",
    "P3278": "male",
    "P2916": "female",
    "P3301": "female",
    "P3285": "male",
    "P3277": "female",
    "P3299": "male",
    "P3029": "male",
    "P2645": "male",
    "P3302": "female",
    "P3286": "male",
    "P3288": "male",
    "P3284": "male",
    "P3310": "male",
    "P3311": "male",
    "P1494": "male",
    "P1499": "female",
    "P1710": "male",
    "P3111": "male",
    "P3101": "male",
    "P1706": "male",
    "P2945": "female",
    "P2211": "male",
    "P3093": "male",
    "P3539": "female",
    "P3551": "male",
    "P2323": "female",
    "P2534": "female",
    "P3488": "female",
    "P3548": "male",
    "P3031": "male",
    "P3191": "female",
    "P3558": "male",
    "P3567": "female",
    "P3561": "male",
    "P3538": "female",
    "P3571": "female",
    "P3502": "male",
    "P3106": "male",
    "P2270": "female",
    "P2610": "female",
    "P3489": "male",
    "P3492": "male",
    "P2815": "male",
    "P3581": "male",
    "P3583": "male",
    "P3573": "female",
    "P2814": "female",
    "P3194": "male",
    "P3585": "female",
    "P5354": "female",
    "P5478": "male",
    "P3574": "female",
    "P5624": "male",
    "P3582": "male",
    "P3575": "male",
    "P3195": "male",
    "P3080": "male",
    "P3422": "male",
    "P4749": "female",
    "P3589": "male",
    "P3121": "male",
    "P3681": "male",
    "P3495": "male",
    "P3602": "male",
    "P3493": "male",
    "P3545": "female",
    "P3513": "male",
    "P3817": "male",
    "P3542": "female",
    "P3547": "male",
    "P3596": "male",
    "P2526": "male",
    "P3606": "male",
    "P3512": "male",
    "P3820": "male",
    "P3819": "male",
    "P2524": "male",
    "P3527": "male",
    "P3601": "female",
    "P3511": "male",
    "P3815": "female",
    "P3814": "male",
    "P3816": "female",
    "P3509": "male",
    "P3600": "male",
    "P3726": "female",
    "P3729": "female",
    "P3734": "female",
    "P2672": "female",
    "P3618": "male",
    "P3624": "male",
    "P3727": "female",
    "P3650": "male",
    "P3614": "male",
    "P3617": "male",
    "P3651": "male",
    "P3733": "male",
    "P3611": "male",
    "P3193": "male",
    "P3622": "male",
    "P2213": "male",
    "P3621": "female",
    "P3633": "male",
    "P3613": "male",
    "P3637": "male",
    "P3666": "male",
    "P3780": "male",
    "P3672": "male",
    "P3736": "female",
    "P2990": "male",
    "P3753": "female",
    "P3772": "female",
    "P3773": "female",
    "P3549": "female",
    "P3738": "female",
    "P3679": "male",
    "P3739": "male",
    "P3743": "male",
    "P3737": "male",
    "P3746": "female",
    "P3751": "female",
    "P3678": "male",
    "P3690": "female",
    "P3691": "male",
    "P3762": "male",
    "P3765": "female",
    "P3766": "male",
    "P3701": "male",
    "P3713": "female",
    "P3721": "male",
    "P3700": "male",
    "P3769": "female",
    "P3496": "male",
    "P3760": "female",
    "P3755": "male",
    "P3754": "male",
    "P3749": "female",
    "P3720": "female",
    "P3761": "male",
    "P2217": "female",
    "P3543": "female",
    "P3844": "male",
    "P3777": "female",
    "P3725": "male",
    "P3783": "male",
    "P3848": "female",
    "P3770": "male",
    "P3852": "female",
    "P3841": "male",
    "P2972": "female",
    "P3771": "male",
    "P3835": "male",
    "P3854": "female",
    "P3856": "male",
    "P3785": "female",
    "P3782": "female",
    "P3775": "male",
    "P3776": "female",
    "P3869": "male",
    "P3897": "female",
    "P3867": "male",
    "P3870": "male",
    "P3898": "female",
    "P3873": "female",
    "P3862": "female",
    "P3896": "male",
    "P3866": "male",
    "P3860": "female",
    "P3879": "male",
    "P3910": "female",
    "P3876": "female",
    "P3861": "male",
    "P3914": "male",
    "P3808": "female",
    "P3885": "male",
    "P3793": "female",
    "P3892": "male",
    "P3887": "male",
    "P3884": "male",
    "P4369": "male",
    "P4684": "male",
    "P3895": "male",
    "P3490": "male",
    "P3927": "male",
    "P3951": "male",
    "P3960": "male",
    "P3933": "male",
    "P3925": "female",
    "P3930": "male",
    "P3923": "male",
    "P3924": "male",
    "P3955": "male",
    "P3950": "male",
    "P3919": "female",
    "P3902": "male",
    "P3941": "male",
    "P3961": "male",
    "P3918": "female",
    "P3948": "male",
    "P3952": "male",
    "P3973": "male",
    "P3981": "male",
    "P3975": "male",
    "P3967": "male",
    "P3972": "male",
    "P3985": "female",
    "P3976": "male",
    "P3978": "female",
    "P4003": "female",
    "P3991": "male",
    "P3971": "male",
    "P3979": "male",
    "P3990": "female",
    "P1560": "male",
    "P3984": "female",
    "P4005": "male",
    "P2244": "female",
    "P2238": "male",
    "P4000": "female",
    "P4006": "male",
    "P3081": "female",
    "P4012": "female",
    "P4030": "male",
    "P4011": "male",
    "P3263": "female",
    "P4308": "female",
    "P4319": "male",
    "P4318": "female",
    "P4326": "male",
    "P4325": "female",
    "P4331": "male",
    "P4329": "male",
    "P4312": "male",
    "P4336": "female",
    "P4330": "female",
    "P4303": "female",
    "P4309": "female",
    "P1762": "female",
    "P4016": "male",
    "P2876": "male",
    "P3890": "female",
    "P4361": "male",
    "P4370": "male",
    "P4379": "female",
    "P4350": "male",
    "P4352": "male",
    "P4421": "male",
    "P4480": "female",
    "P4711": "male",
    "P4342": "female",
    "P4349": "male",
    "P4679": "male",
    "P4395": "female",
    "P4471": "female",
    "P4408": "male",
    "P4420": "female",
    "P4473": "female",
    "P4709": "female",
    "P4406": "female",
    "P4409": "female",
    "P4478": "female",
    "P4487": "male",
    "P4400": "female",
    "P4359": "female",
    "P4470": "female",
    "P3570": "female",
    "P4477": "female",
    "P4402": "female",
    "P4403": "male",
    "P4488": "female",
    "P4708": "male",
    "P4396": "male",
    "P4678": "male",
    "P2790": "male",
    "P4714": "male",
    "P4269": "female",
    "P4295": "male",
    "P4288": "female",
    "P4289": "male",
    "P4290": "female",
    "P4298": "female",
    "P4283": "female",
    "P4279": "male",
    "P4296": "male",
    "P4277": "male",
    "P4299": "male",
    "P4291": "female",
    "P4284": "female",
    "P4292": "male",
    "P4282": "female",
    "P4343": "female",
    "P4294": "male",
    "P4281": "female",
    "P4275": "female",
    "P4280": "female",
    "P4419": "male",
    "P4412": "female",
    "P4413": "male",
    "P4414": "male",
    "P4417": "female",
    "P4415": "male",
    "P4347": "male",
    "P4363": "male",
    "P4416": "male",
    "P4425": "female",
    "P4404": "male",
    "P4344": "male",
    "P4399": "male",
    "P4405": "female",
    "P4426": "male",
    "P4431": "male",
    "P4428": "male",
    "P4430": "male",
    "P4455": "male",
    "P4454": "female",
    "P4427": "male",
    "P4438": "female",
    "P4286": "male",
    "P4462": "female",
    "P4441": "male",
    "P4440": "male",
    "P4439": "male",
    "P4652": "female",
    "P4634": "female",
    "P4560": "male",
    "P4570": "male",
    "P4673": "male",
    "P4663": "female",
    "P4561": "female",
    "P4612": "male",
    "P4672": "male",
    "P2642": "male",
    "P4581": "female",
    "P4588": "female",
    "P2640": "female",
    "P4583": "male",
    "P4273": "male",
    "P4423": "male",
    "P4272": "male",
    "P4610": "female",
    "P4597": "male",
    "P4582": "male",
    "P4584": "male",
    "P4589": "female",
    "P4586": "male",
    "P4569": "female",
    "P4596": "female",
    "P4626": "female",
    "P4623": "male",
    "P4445": "male",
    "P4615": "male",
    "P4593": "male",
    "P4604": "male",
    "P4620": "male",
    "P4630": "female",
    "P4625": "male",
    "P4631": "female",
    "P4614": "female",
    "P4638": "male",
    "P4649": "male",
    "P4645": "male",
    "P4648": "male",
    "P4619": "female",
    "P4600": "male",
    "P4605": "female",
    "P4643": "female",
    "P4688": "male",
    "P4744": "male",
    "P4737": "female",
    "P4680": "male",
    "P4686": "male",
    "P4745": "male",
    "P4696": "female",
    "P4735": "male",
    "P4755": "female",
    "P4766": "female",
    "P4786": "male",
    "P4790": "female",
    "P4752": "male",
    "P4767": "male",
    "P3994": "male",
    "P4773": "male",
    "P4789": "female",
    "P4760": "female",
    "P4772": "male",
    "P4787": "female",
    "P4761": "female",
    "P4763": "female",
    "P4751": "male",
    "P4765": "female",
    "P4750": "male",
    "P4788": "male",
    "P4792": "female",
    "P4796": "female",
    "P4822": "male",
    "P4932": "female",
    "P4823": "female",
    "P4928": "female",
    "P4802": "male",
    "P4815": "male",
    "P4812": "male",
    "P4843": "male",
    "P4868": "male",
    "P4867": "male",
    "P4875": "female",
    "P4801": "female",
    "P4876": "female",
    "P4863": "female",
    "P3049": "male",
    "P4866": "female",
    "P4878": "female",
    "P4904": "female",
    "P4916": "female",
    "P4896": "male",
    "P4912": "male",
    "P4907": "female",
    "P4905": "female",
    "P4931": "male",
    "P4895": "male",
    "P4897": "male",
    "P4918": "female",
    "P4921": "male",
    "P4926": "female",
    "P4917": "male",
    "P4894": "female",
    "P4927": "female",
    "P4951": "female",
    "P4941": "female",
    "P4940": "male",
    "P4969": "male",
    "P4937": "male",
    "P4943": "male",
    "P4944": "female",
    "P4946": "female",
    "P4950": "male",
    "P5069": "female",
    "P4817": "male",
    "P4784": "female",
    "P5104": "female",
    "P4731": "female",
    "P4799": "female",
    "P4730": "male",
    "P4785": "male",
    "P4816": "male",
    "P5081": "male",
    "P4997": "male",
    "P4738": "male",
    "P4992": "male",
    "P4978": "female",
    "P4756": "male",
    "P4990": "female",
    "P4991": "male",
    "P4757": "male",
    "P4975": "male",
    "P4782": "male",
    "P4774": "female",
    "P4982": "male",
    "P4783": "female",
    "P4958": "female",
    "P3046": "female",
    "P4959": "male",
    "P5303": "male",
    "P5347": "male",
    "P5308": "male",
    "P5309": "male",
    "P5365": "male",
    "P5381": "female",
    "P5386": "female",
    "P2894": "female",
    "P5395": "male",
    "P5360": "female",
    "P5367": "female",
    "P5364": "male",
    "P5370": "female",
    "P5380": "male",
    "P5387": "male",
    "P5394": "female",
    "P5404": "female",
    "P5321": "male",
    "P5341": "male",
    "P5315": "male",
    "P5305": "male",
    "P5318": "male",
    "P5322": "female",
    "P5345": "female",
    "P5299": "male",
    "P5317": "female",
    "P5352": "male",
    "P5331": "male",
    "P5314": "male",
    "P5298": "male",
    "P5445": "female",
    "P5336": "male",
    "P5316": "male",
    "P5351": "male",
    "P5400": "female",
    "P5424": "female",
    "P5393": "female",
    "P5401": "male",
    "P5411": "female",
    "P5407": "female",
    "P5391": "male",
    "P5398": "male",
    "P5414": "male",
    "P5356": "male",
    "P5358": "male",
    "P5428": "male",
    "P5434": "male",
    "P5432": "female",
    "P5448": "male",
    "P5439": "male",
    "P5446": "male",
    "P5431": "male",
    "P5437": "male",
    "P5489": "male",
    "P5457": "female",
    "P5497": "male",
    "P5442": "female",
    "P5476": "female",
    "P5509": "female",
    "P5456": "male",
    "P5518": "male",
    "P5488": "male",
    "P5485": "male",
    "P5466": "male",
    "P5455": "female",
    "P5474": "male",
    "P5556": "female",
    "P5522": "female",
    "P5454": "male",
    "P5460": "male",
    "P5525": "male",
    "P5479": "male",
    "P5470": "male",
    "P5486": "male",
    "P5487": "male",
    "P5481": "female",
    "P5529": "male",
    "P5555": "male",
    "P5539": "male",
    "P5547": "male",
    "P5549": "male",
    "P5542": "male",
    "P5543": "female",
    "P5473": "male",
    "P5579": "female",
    "P5535": "male",
    "P5546": "male",
    "P5531": "female",
    "P5554": "female",
    "P5538": "male",
    "P5491": "male",
    "P5588": "male",
    "P5612": "male",
    "P5637": "male",
    "P5599": "female",
    "P5594": "male",
    "P5649": "female",
    "P5631": "male",
    "P5626": "male",
    "P5641": "female",
    "P5583": "female",
    "P5609": "female",
    "P5590": "male",
    "P5608": "female",
    "P5647": "female",
    "P5582": "female",
    "P5595": "female",
    "P5619": "female",
    "P5627": "male",
    "P5616": "male",
    "P5701": "male",
    "P5712": "male",
    "P3024": "male",
    "P5652": "female",
    "P5683": "female",
    "P5717": "male",
    "P5716": "male",
    "P5702": "male",
    "P5696": "male",
    "P5715": "female",
    "P5771": "male",
    "P5742": "male",
    "P5782": "male",
    "P5726": "female",
    "P5767": "female",
    "P5753": "female",
    "P5760": "male",
    "P5786": "male",
    "P5746": "male",
    "P5728": "male",
    "P5747": "female",
    "P5744": "female",
    "P5748": "male",
    "P5775": "female",
    "P5727": "female",
    "P5736": "female",
    "P5725": "male",
    "P5693": "male",
    "P5808": "male",
    "P5802": "female",
    "P5793": "male",
    "P5805": "female",
    "P5692": "male",
    "P5800": "female",
    "P5792": "male",
    "P5814": "female",
    "P5796": "male",
    "P5790": "male",
    "P5809": "female",
    "P5804": "female"
}